my_timer_decorator/__init__.py
shancx/__init__.py
shancx/draw_day_CR_PNG.py
shancx/draw_day_CR_SVG.py
shancx/mkIMGSCX.py
shancx/radar_nmc.py
shancx/radar_nmc_china_map_compare1.py
shancx/radar_nmc_china_map_f.py
shancx/subplots_compare_devlop.py
shancx/subplots_single_china_map.py
shancx/tool.py
shancx/util_log.py
shancx/E/__init__.py
shancx/M/__init__.py
shancx/N/__init__.py
shancx/S/__init__.py
shancx/W/__init__.py
shancx/user/H8mess.py
shancx/user/__init__.py
shancx/user/cinradHJN.py
shancx/user/examMeso.py
shancx/user/hjnDAAS.py
shancx/user/hjnFTP.py
shancx/user/hjnGIS.py
shancx/user/hjnGPU.py
shancx/user/hjnIDW.py
shancx/user/hjnKDTree.py
shancx/user/hjnLAPSTransform.py
shancx/user/hjnMiscellaneous.py
shancx/user/hjnProj.py
shancx/user/inotify.py
shancx/user/matplotlibMess.py
shancx/user/mkNCHJN.py
shancx/user/newTypeRadar.py
shancx/user/test.py
shancx/user/tlogP.py
shancx/wtx/H8mess.py
shancx/wtx/__init__.py
shancx/wtx/cinradHJN.py
shancx/wtx/colormap.py
shancx/wtx/examMeso.py
shancx/wtx/hjnDAAS.py
shancx/wtx/hjnFTP.py
shancx/wtx/hjnGIS.py
shancx/wtx/hjnGPU.py
shancx/wtx/hjnIDW.py
shancx/wtx/hjnKDTree.py
shancx/wtx/hjnLAPSTransform.py
shancx/wtx/hjnLog.py
shancx/wtx/hjnMiscellaneous.py
shancx/wtx/hjnProj.py
shancx/wtx/inotify.py
shancx/wtx/matplotlibMess.py
shancx/wtx/mkNCHJN.py
shancx/wtx/newTypeRadar.py
shancx/wtx/test.py
shancx/wtx/tlogP.py
shancxwtx/__init__.py
shancxwtx/draw_day_CR_PNG.py
shancxwtx/draw_day_CR_SVG.py
shancxwtx/mkIMGSCX.py
shancxwtx/radar_nmc.py
shancxwtx/radar_nmc_china_map_compare1.py
shancxwtx/radar_nmc_china_map_f.py
shancxwtx/subplots_compare_devlop.py
shancxwtx/subplots_single_china_map.py
shancxwtx/tool.py
shancxwtx/E/__init__.py
shancxwtx/M/__init__.py
shancxwtx/N/__init__.py
shancxwtx/S/__init__.py
shancxwtx/W/__init__.py
shancxwtx/user/H8mess.py
shancxwtx/user/__init__.py
shancxwtx/user/cinradHJN.py
shancxwtx/user/examMeso.py
shancxwtx/user/hjnDAAS.py
shancxwtx/user/hjnFTP.py
shancxwtx/user/hjnGIS.py
shancxwtx/user/hjnGPU.py
shancxWTX-1.8.26.dist-info/METADATA
shancxWTX-1.8.26.dist-info/WHEEL
shancxWTX-1.8.26.dist-info/top_level.txt
shancxWTX-1.8.26.dist-info/RECORD
