Metadata-Version: 2.1
Name: shancxWTX
Version: 1.8.26
Summary: A simple timer decorator
Home-page: https://gitee.com/shancx
Author: shancx
Author-email: your.email@example.com
Classifier: Programming Language :: Python :: 3
Classifier: License :: OSI Approved :: MIT License
Classifier: Operating System :: OS Independent
Requires-Python: >=3.6
Requires-Dist: numpy >=0
